{
  "type": "FeatureCollection",
  "properties": {
    "Nome": "ULS018_Riparo_Gabellaccia2",
    "Descrizione": "",
    "umapKey": "https://umap.openstreetmap.fr/it/map/uls018_riparogabellaccia2_1062930"
  },
  "features": [
    {
      "geometry": {
        "coordinates": [
          10.094682,
          44.123728
        ],
        "type": "Point"
      },
      "properties": {
        "ulsp_type": "Sito",
        "Titolo": "Riparo della Gabellaccia 2",
        "Descrizione": "Grande riparo sotto roccia con ampia apertura  e camera più profonda sulla destra, importante vegetazione invade l'interno",
        "Data": "02-15-2024",
        "Ora": "11:32:42 AM",
        "Sito": "ULS018",
        "Provincia": "Massa Carrara",
        "Comune": "Carrara",
        "Toponimo": "Passo della Gabellaccia",
        "Microtoponimo": "",
        "Altitudine": 821,
        "Strade d'accesso": "sentiero 185, partendo dal passo della Gabellaccia, pochi metri dopo il riparo della Gabellaccia 1, in direzione ovest, seguendo una traccia",
        "Altri elementi di localizzazione": "",
        "Tipologia sito": "ND",
        "Definizione": "",
        "Cronologia iniziale": "ND (Non determinata)",
        "Cronologia finale": "ND (Non determinata)",
        "Reperti ceramici": "NO",
        "Reperti geologici": "NO",
        "Reperti organici": "NO",
        "Altri manufatti": "",
        "Sicurezza": "semplice raggiungere il sito",
        "Accessibilità": "Facile",
        "Copertura rete mobile": "Parziale",
        "Copertura GPS": "Parziale",
        "Foto": "",
        "Link": "",
        "Bibliografia": "",
        "Strumento": ""
      },
      "type": "Feature"
    }
  ]
}